treeage/__init__.py
treeage/__version__.py
treeage/core.py
treeage/terminal.py
treeage-0.3.0.dist-info/LICENSE
treeage-0.3.0.dist-info/METADATA
treeage-0.3.0.dist-info/WHEEL
treeage-0.3.0.dist-info/entry_points.txt
treeage-0.3.0.dist-info/top_level.txt
treeage-0.3.0.dist-info/RECORD
