Metadata-Version: 2.1
Name: treeage
Version: 0.3.0
Summary: Lists contents of directories in a tree-like format with age metric indicated for each file
Home-page: https://github.com/KraYmer/treeage
Author: Fabrice Laporte
Author-email: kraymer@gmail.com
License: MIT
Keywords: git
Platform: ALL
Classifier: License :: OSI Approved :: MIT License
Classifier: Programming Language :: Python
Classifier: Environment :: Console
Classifier: Topic :: System :: Filesystems
Requires-Dist: arrow
Requires-Dist: blessed
Requires-Dist: click
Requires-Dist: click-log
Requires-Dist: dateparser
Requires-Dist: gitpython
Provides-Extra: test
Requires-Dist: coverage (>5) ; extra == 'test'
Requires-Dist: pytest (>=6) ; extra == 'test'
Requires-Dist: tox (>=3) ; extra == 'test'
